pi_stream_util/__init__.py
pi_stream_util/__version__.py
pi_stream_util/py.typed
pi_stream_util/stream.py
pi_stream_util-0.1.0.dist-info/LICENSE
pi_stream_util-0.1.0.dist-info/METADATA
pi_stream_util-0.1.0.dist-info/WHEEL
pi_stream_util-0.1.0.dist-info/top_level.txt
pi_stream_util-0.1.0.dist-info/RECORD
