Metadata-Version: 2.1
Name: pi-stream-util
Version: 0.1.0
Summary: Self managed stream processor for PI Web API Channels
Home-page: https://github.com/newvicx/pi_stream_util
Author: Chris Newville
Author-email: chrisnewville1396@gmail.com
License: MIT
Project-URL: Changelog, https://github.com/newvicx/pi_stream_util/blob/master/CHANGELOG.md
Project-URL: Source, https://github.com/newvicx/pi_stream_util
Platform: UNKNOWN
Classifier: Development Status :: 4 - Beta
Classifier: Environment :: Web Environment
Classifier: Intended Audience :: Developers
Classifier: License :: OSI Approved :: MIT License
Classifier: Operating System :: Microsoft :: Windows
Classifier: Topic :: Internet :: WWW/HTTP
Classifier: Framework :: AsyncIO
Classifier: Programming Language :: Python :: 3
Classifier: Programming Language :: Python :: 3.9
Classifier: Programming Language :: Python :: 3.10
Classifier: Programming Language :: Python :: 3 :: Only
Requires-Python: >=3.9
License-File: LICENSE
Requires-Dist: piwebasync (>=0.1.1)
